cactive_hypixel_nick_tracker/__init__.py
cactive_hypixel_nick_tracker/classes.py
cactive_hypixel_nick_tracker-3.0.6.dist-info/LICENSE.md
cactive_hypixel_nick_tracker-3.0.6.dist-info/METADATA
cactive_hypixel_nick_tracker-3.0.6.dist-info/WHEEL
cactive_hypixel_nick_tracker-3.0.6.dist-info/top_level.txt
cactive_hypixel_nick_tracker-3.0.6.dist-info/RECORD
