Metadata-Version: 2.1
Name: cactive-hypixel-nick-tracker
Version: 3.0.6
Summary: Wrapper for the exclusive CactiveNetwork unofficial Hypixel API.
Home-page: https://github.com/CactiveNetwork/cactive-rewrites/tree/main/python/hypixel-nick-tracker
Author: Cactive
Author-email: legal@cactive.network
Project-URL: Bug Tracker, https://github.com/CactiveNetwork/cactive-rewrites/tree/main/python/hypixel-nick-tracker/issues
Classifier: Programming Language :: Python :: 3
Classifier: License :: Other/Proprietary License
Classifier: Operating System :: OS Independent
Requires-Python: >=3.9
License-File: LICENSE.md
Requires-Dist: requests (==2.28.1)
